CHANGELOG.md
MANIFEST.in
README.md
requirements.txt
setup.py
keras_gradient_accumulation/__init__.py
keras_gradient_accumulation/backend.py
keras_gradient_accumulation/optimizer_v1.py
keras_gradient_accumulation/optimizer_v2.py
keras_gradient_accumulation/optimizers.py
keras_gradient_accumulation/selection.py
keras_gradient_accumulation.egg-info/PKG-INFO
keras_gradient_accumulation.egg-info/SOURCES.txt
keras_gradient_accumulation.egg-info/dependency_links.txt
keras_gradient_accumulation.egg-info/requires.txt
keras_gradient_accumulation.egg-info/top_level.txt
tests/__init__.py
tests/test_optimizers.py