Metadata-Version: 2.1
Name: keras-gradient-accumulation
Version: 0.0.6
Summary: Gradient accumulation for Keras
Home-page: https://github.com/CyberZHG/keras-gradient-accumulation
Author: CyberZHG
Author-email: CyberZHG@users.noreply.github.com
License: MIT
Platform: UNKNOWN
Classifier: Programming Language :: Python :: 3
Classifier: License :: OSI Approved :: MIT License
Classifier: Operating System :: OS Independent
